css_bundler-0.1.1.dist-info/METADATA
css_bundler-0.1.1.dist-info/WHEEL
css_bundler-0.1.1.dist-info/entry_points.txt
css_bundler/__init__.py
css_bundler-0.1.1.dist-info/RECORD
