Metadata-Version: 2.1
Name: css-bundler
Version: 0.1.1
Summary: Simple CSS bundler in Python.
Author-Email: Sergei Minaev <i@zenux.ru>
License: MIT
Requires-Python: >=3.8
